openmcmc/__init__.py
openmcmc/distribution/__init__.py
openmcmc/distribution/distribution.py
openmcmc/distribution/location_scale.py
openmcmc/gmrf.py
openmcmc/mcmc.py
openmcmc/model.py
openmcmc/parameter.py
openmcmc/sampler/__init__.py
openmcmc/sampler/metropolis_hastings.py
openmcmc/sampler/reversible_jump.py
openmcmc/sampler/sampler.py
openmcmc-1.0.8.dist-info/METADATA
openmcmc-1.0.8.dist-info/WHEEL
openmcmc-1.0.8.dist-info/licenses/LICENSE.md
openmcmc-1.0.8.dist-info/licenses/LICENSES/Apache-2.0.txt
openmcmc-1.0.8.dist-info/RECORD
