Metadata-Version: 2.4
Name: openmcmc
Version: 1.0.8
Summary: openMCMC tools
License: Apache-2.0
License-File: LICENSE.md
License-File: LICENSES/Apache-2.0.txt
Keywords: Markov Chain Monte Carlo,MCMC
Author: Bas van de Kerkhof
Requires-Python: >=3.11
Classifier: License :: OSI Approved :: Apache Software License
Classifier: Programming Language :: Python :: 3
Classifier: Programming Language :: Python :: 3.11
Classifier: Programming Language :: Python :: 3.12
Classifier: Programming Language :: Python :: 3.13
Classifier: Programming Language :: Python :: 3.14
Provides-Extra: extras
Requires-Dist: matplotlib (>=3.10.8) ; extra == "extras"
Requires-Dist: numpy (>=2.4.0)
Requires-Dist: pandas (>=2.3.3)
Requires-Dist: pytictoc (>=1.5.3) ; extra == "extras"
Requires-Dist: scipy (>=1.16.3)
Requires-Dist: tqdm (>=4.67.1)
Project-URL: Documentation, https://sede-open.github.io/openMCMC/
Project-URL: Homepage, https://sede-open.github.io/openMCMC/
Project-URL: Repository, https://github.com/sede-open/openMCMC
